{
    "Meta Data": {
        "1. Information": "Daily Prices (open, high, low, close) and Volumes",
        "2. Symbol": "TSCO.LON",
        "3. Last Refreshed": "2025-06-19",
        "4. Output Size": "Compact",
        "5. Time Zone": "US/Eastern"
    },
    "Time Series (Daily)": {
        "2025-06-19": {
            "1. open": "402.0000",
            "2. high": "404.6005",
            "3. low": "400.7000",
            "4. close": "402.2000",
            "5. volume": "13218952"
        },
        "2025-06-18": {
            "1. open": "398.2000",
            "2. high": "401.5490",
            "3. low": "397.6000",
            "4. close": "400.8000",
            "5. volume": "18926270"
        },
        "2025-06-17": {
            "1. open": "393.6000",
            "2. high": "396.2000",
            "3. low": "392.3520",
            "4. close": "396.2000",
            "5. volume": "11570220"
        },
        "2025-06-16": {
            "1. open": "396.8000",
            "2. high": "397.8000",
            "3. low": "394.0000",
            "4. close": "394.1000",
            "5. volume": "23145430"
        },
        "2025-06-13": {
            "1. open": "387.6000",
            "2. high": "399.3000",
            "3. low": "386.8000",
            "4. close": "398.2000",
            "5. volume": "15913180"
        },
        "2025-06-12": {
            "1. open": "389.4000",
            "2. high": "397.6000",
            "3. low": "385.2000",
            "4. close": "391.6000",
            "5. volume": "23315789"
        },
        "2025-06-11": {
            "1. open": "384.3000",
            "2. high": "386.8000",
            "3. low": "382.4200",
            "4. close": "385.3000",
            "5. volume": "18777961"
        },
        "2025-06-10": {
            "1. open": "386.4000",
            "2. high": "387.3000",
            "3. low": "382.9000",
            "4. close": "385.5000",
            "5. volume": "12563980"
        },
        "2025-06-09": {
            "1. open": "391.9000",
            "2. high": "392.1000",
            "3. low": "383.2500",
            "4. close": "384.6000",
            "5. volume": "16308500"
        },
        "2025-06-06": {
            "1. open": "387.8000",
            "2. high": "392.4000",
            "3. low": "385.9000",
            "4. close": "390.6000",
            "5. volume": "12834650"
        },
        "2025-06-05": {
            "1. open": "388.5000",
            "2. high": "389.7000",
            "3. low": "385.0000",
            "4. close": "387.3000",
            "5. volume": "15886170"
        },
        "2025-06-04": {
            "1. open": "390.5000",
            "2. high": "391.7000",
            "3. low": "387.6980",
            "4. close": "388.6000",
            "5. volume": "14450670"
        },
        "2025-06-03": {
            "1. open": "397.9000",
            "2. high": "398.3000",
            "3. low": "390.0000",
            "4. close": "390.0000",
            "5. volume": "17578070"
        },
        "2025-06-02": {
            "1. open": "388.4000",
            "2. high": "391.8000",
            "3. low": "387.4000",
            "4. close": "390.6000",
            "5. volume": "26933199"
        },
        "2025-05-30": {
            "1. open": "384.7000",
            "2. high": "391.2000",
            "3. low": "383.7000",
            "4. close": "388.0000",
            "5. volume": "27554891"
        },
        "2025-05-29": {
            "1. open": "385.6000",
            "2. high": "385.9000",
            "3. low": "376.9000",
            "4. close": "382.5000",
            "5. volume": "15783560"
        },
        "2025-05-28": {
            "1. open": "388.0000",
            "2. high": "389.7000",
            "3. low": "385.4000",
            "4. close": "385.4000",
            "5. volume": "28804400"
        },
        "2025-05-27": {
            "1. open": "382.6000",
            "2. high": "387.5490",
            "3. low": "381.6000",
            "4. close": "386.8000",
            "5. volume": "23069080"
        },
        "2025-05-23": {
            "1. open": "381.1000",
            "2. high": "384.8000",
            "3. low": "379.9000",
            "4. close": "381.7000",
            "5. volume": "34675832"
        },
        "2025-05-22": {
            "1. open": "379.2000",
            "2. high": "383.4000",
            "3. low": "378.4000",
            "4. close": "381.5000",
            "5. volume": "23353150"
        },
        "2025-05-21": {
            "1. open": "377.2000",
            "2. high": "380.6000",
            "3. low": "376.0982",
            "4. close": "380.6000",
            "5. volume": "17127631"
        },
        "2025-05-20": {
            "1. open": "372.5000",
            "2. high": "378.8000",
            "3. low": "370.1000",
            "4. close": "377.9000",
            "5. volume": "20048820"
        },
        "2025-05-19": {
            "1. open": "365.3000",
            "2. high": "371.1000",
            "3. low": "365.0978",
            "4. close": "371.1000",
            "5. volume": "23277150"
        },
        "2025-05-16": {
            "1. open": "366.1000",
            "2. high": "369.6000",
            "3. low": "362.9000",
            "4. close": "362.9000",
            "5. volume": "42015551"
        },
        "2025-05-15": {
            "1. open": "360.0000",
            "2. high": "364.6000",
            "3. low": "357.5600",
            "4. close": "363.7000",
            "5. volume": "29879900"
        },
        "2025-05-14": {
            "1. open": "364.2000",
            "2. high": "370.2000",
            "3. low": "362.6000",
            "4. close": "368.1000",
            "5. volume": "17353391"
        },
        "2025-05-13": {
            "1. open": "367.3000",
            "2. high": "370.9000",
            "3. low": "365.7000",
            "4. close": "366.5000",
            "5. volume": "11558930"
        },
        "2025-05-12": {
            "1. open": "379.0000",
            "2. high": "379.9000",
            "3. low": "366.1000",
            "4. close": "368.7000",
            "5. volume": "19092551"
        },
        "2025-05-09": {
            "1. open": "379.1000",
            "2. high": "380.1000",
            "3. low": "375.2980",
            "4. close": "377.7000",
            "5. volume": "15241340"
        },
        "2025-05-08": {
            "1. open": "380.6000",
            "2. high": "382.8000",
            "3. low": "375.8000",
            "4. close": "377.2000",
            "5. volume": "16602641"
        },
        "2025-05-07": {
            "1. open": "377.5000",
            "2. high": "379.2000",
            "3. low": "374.6000",
            "4. close": "379.2000",
            "5. volume": "33015859"
        },
        "2025-05-06": {
            "1. open": "374.2000",
            "2. high": "380.1000",
            "3. low": "373.8000",
            "4. close": "376.8000",
            "5. volume": "12905030"
        },
        "2025-05-02": {
            "1. open": "372.8000",
            "2. high": "377.5000",
            "3. low": "371.0000",
            "4. close": "371.0000",
            "5. volume": "40736219"
        },
        "2025-05-01": {
            "1. open": "371.9000",
            "2. high": "373.1000",
            "3. low": "368.5000",
            "4. close": "372.5000",
            "5. volume": "12743230"
        },
        "2025-04-30": {
            "1. open": "366.1000",
            "2. high": "371.6000",
            "3. low": "365.5000",
            "4. close": "370.7000",
            "5. volume": "36491406"
        },
        "2025-04-29": {
            "1. open": "358.3000",
            "2. high": "366.0000",
            "3. low": "356.4000",
            "4. close": "364.9000",
            "5. volume": "16949811"
        },
        "2025-04-28": {
            "1. open": "359.5000",
            "2. high": "360.6000",
            "3. low": "355.7000",
            "4. close": "357.3000",
            "5. volume": "33908609"
        },
        "2025-04-25": {
            "1. open": "358.3000",
            "2. high": "364.1000",
            "3. low": "357.9000",
            "4. close": "357.9000",
            "5. volume": "34230887"
        },
        "2025-04-24": {
            "1. open": "360.9000",
            "2. high": "363.5000",
            "3. low": "358.4000",
            "4. close": "360.3000",
            "5. volume": "41237121"
        },
        "2025-04-23": {
            "1. open": "357.6000",
            "2. high": "359.8000",
            "3. low": "353.2000",
            "4. close": "357.7000",
            "5. volume": "22633119"
        },
        "2025-04-22": {
            "1. open": "356.6000",
            "2. high": "365.0000",
            "3. low": "356.5000",
            "4. close": "359.9000",
            "5. volume": "21298680"
        },
        "2025-04-17": {
            "1. open": "343.6000",
            "2. high": "355.3000",
            "3. low": "343.6000",
            "4. close": "354.6000",
            "5. volume": "21422609"
        },
        "2025-04-16": {
            "1. open": "346.0000",
            "2. high": "350.0500",
            "3. low": "344.9000",
            "4. close": "345.6000",
            "5. volume": "21873631"
        },
        "2025-04-15": {
            "1. open": "337.8000",
            "2. high": "345.9000",
            "3. low": "337.2250",
            "4. close": "345.5000",
            "5. volume": "36426512"
        },
        "2025-04-14": {
            "1. open": "332.0000",
            "2. high": "337.7000",
            "3. low": "330.0000",
            "4. close": "336.4000",
            "5. volume": "22515461"
        },
        "2025-04-11": {
            "1. open": "317.4000",
            "2. high": "328.1000",
            "3. low": "314.9000",
            "4. close": "327.7000",
            "5. volume": "31430090"
        },
        "2025-04-10": {
            "1. open": "320.0000",
            "2. high": "326.5040",
            "3. low": "310.3000",
            "4. close": "314.6000",
            "5. volume": "49332461"
        },
        "2025-04-09": {
            "1. open": "334.9000",
            "2. high": "336.8370",
            "3. low": "328.7000",
            "4. close": "335.2000",
            "5. volume": "22844141"
        },
        "2025-04-08": {
            "1. open": "328.0000",
            "2. high": "338.4000",
            "3. low": "323.8000",
            "4. close": "337.4000",
            "5. volume": "17610590"
        },
        "2025-04-07": {
            "1. open": "337.9000",
            "2. high": "339.6000",
            "3. low": "325.5000",
            "4. close": "327.1000",
            "5. volume": "24107830"
        },
        "2025-04-04": {
            "1. open": "346.3000",
            "2. high": "350.1000",
            "3. low": "340.0000",
            "4. close": "340.0000",
            "5. volume": "20674211"
        },
        "2025-04-03": {
            "1. open": "333.2000",
            "2. high": "347.2000",
            "3. low": "331.7863",
            "4. close": "345.6000",
            "5. volume": "30187471"
        },
        "2025-04-02": {
            "1. open": "329.1000",
            "2. high": "332.3000",
            "3. low": "328.7000",
            "4. close": "331.1000",
            "5. volume": "12132090"
        },
        "2025-04-01": {
            "1. open": "332.9000",
            "2. high": "334.7000",
            "3. low": "321.5000",
            "4. close": "330.0000",
            "5. volume": "16470930"
        },
        "2025-03-31": {
            "1. open": "330.0000",
            "2. high": "333.3000",
            "3. low": "327.3300",
            "4. close": "332.3000",
            "5. volume": "16215490"
        },
        "2025-03-28": {
            "1. open": "329.1000",
            "2. high": "335.4000",
            "3. low": "328.7000",
            "4. close": "332.3000",
            "5. volume": "26757570"
        },
        "2025-03-27": {
            "1. open": "333.1000",
            "2. high": "336.0000",
            "3. low": "327.1000",
            "4. close": "329.3000",
            "5. volume": "13235090"
        },
        "2025-03-26": {
            "1. open": "330.6000",
            "2. high": "334.1000",
            "3. low": "329.9000",
            "4. close": "332.7000",
            "5. volume": "41366793"
        },
        "2025-03-25": {
            "1. open": "327.6000",
            "2. high": "330.2000",
            "3. low": "326.2000",
            "4. close": "329.8000",
            "5. volume": "45545102"
        },
        "2025-03-24": {
            "1. open": "324.8000",
            "2. high": "326.5000",
            "3. low": "322.0000",
            "4. close": "325.8000",
            "5. volume": "14487390"
        },
        "2025-03-21": {
            "1. open": "324.7000",
            "2. high": "326.2000",
            "3. low": "320.6000",
            "4. close": "325.6000",
            "5. volume": "44763359"
        },
        "2025-03-20": {
            "1. open": "321.0000",
            "2. high": "324.6000",
            "3. low": "319.5000",
            "4. close": "324.0000",
            "5. volume": "29155650"
        },
        "2025-03-19": {
            "1. open": "325.3000",
            "2. high": "326.2000",
            "3. low": "318.9000",
            "4. close": "321.3000",
            "5. volume": "21992830"
        },
        "2025-03-18": {
            "1. open": "326.6000",
            "2. high": "329.2000",
            "3. low": "321.8000",
            "4. close": "326.1000",
            "5. volume": "20839891"
        },
        "2025-03-17": {
            "1. open": "338.3000",
            "2. high": "339.0550",
            "3. low": "321.8000",
            "4. close": "324.2000",
            "5. volume": "44177930"
        },
        "2025-03-14": {
            "1. open": "371.7000",
            "2. high": "371.7000",
            "3. low": "337.8700",
            "4. close": "339.2000",
            "5. volume": "36864633"
        },
        "2025-03-13": {
            "1. open": "372.9000",
            "2. high": "376.2000",
            "3. low": "369.4000",
            "4. close": "371.5000",
            "5. volume": "11345770"
        },
        "2025-03-12": {
            "1. open": "371.9000",
            "2. high": "375.0000",
            "3. low": "369.3000",
            "4. close": "375.0000",
            "5. volume": "9988516"
        },
        "2025-03-11": {
            "1. open": "377.0000",
            "2. high": "378.3000",
            "3. low": "368.6000",
            "4. close": "370.0000",
            "5. volume": "24816680"
        },
        "2025-03-10": {
            "1. open": "380.8000",
            "2. high": "382.2000",
            "3. low": "377.5000",
            "4. close": "378.1000",
            "5. volume": "36151871"
        },
        "2025-03-07": {
            "1. open": "376.2000",
            "2. high": "380.1000",
            "3. low": "372.4000",
            "4. close": "380.1000",
            "5. volume": "9108571"
        },
        "2025-03-06": {
            "1. open": "381.4000",
            "2. high": "381.4000",
            "3. low": "371.6000",
            "4. close": "375.9000",
            "5. volume": "24988850"
        },
        "2025-03-05": {
            "1. open": "386.2000",
            "2. high": "387.8000",
            "3. low": "379.0000",
            "4. close": "379.0000",
            "5. volume": "51508859"
        },
        "2025-03-04": {
            "1. open": "377.2000",
            "2. high": "389.3335",
            "3. low": "376.7000",
            "4. close": "388.7000",
            "5. volume": "26635199"
        },
        "2025-03-03": {
            "1. open": "380.0000",
            "2. high": "380.6000",
            "3. low": "375.2000",
            "4. close": "378.0000",
            "5. volume": "18746279"
        },
        "2025-02-28": {
            "1. open": "378.3000",
            "2. high": "382.1000",
            "3. low": "377.4390",
            "4. close": "380.2000",
            "5. volume": "19236080"
        },
        "2025-02-27": {
            "1. open": "375.8000",
            "2. high": "381.3000",
            "3. low": "374.8960",
            "4. close": "379.4000",
            "5. volume": "9043657"
        },
        "2025-02-26": {
            "1. open": "376.6000",
            "2. high": "379.1000",
            "3. low": "376.1000",
            "4. close": "378.1000",
            "5. volume": "10126300"
        },
        "2025-02-25": {
            "1. open": "375.5000",
            "2. high": "377.4000",
            "3. low": "373.6200",
            "4. close": "375.5000",
            "5. volume": "20791279"
        },
        "2025-02-24": {
            "1. open": "375.9000",
            "2. high": "376.4000",
            "3. low": "372.0000",
            "4. close": "376.1000",
            "5. volume": "29891119"
        },
        "2025-02-21": {
            "1. open": "375.4000",
            "2. high": "377.8000",
            "3. low": "372.9000",
            "4. close": "374.1000",
            "5. volume": "21949500"
        },
        "2025-02-20": {
            "1. open": "381.7000",
            "2. high": "382.6000",
            "3. low": "374.0000",
            "4. close": "374.8000",
            "5. volume": "28276910"
        },
        "2025-02-19": {
            "1. open": "382.2000",
            "2. high": "385.1000",
            "3. low": "379.8000",
            "4. close": "380.9000",
            "5. volume": "14086530"
        },
        "2025-02-18": {
            "1. open": "393.3000",
            "2. high": "394.2000",
            "3. low": "382.3000",
            "4. close": "382.3000",
            "5. volume": "23268119"
        },
        "2025-02-17": {
            "1. open": "396.4000",
            "2. high": "397.1000",
            "3. low": "394.1000",
            "4. close": "397.0000",
            "5. volume": "6494760"
        },
        "2025-02-14": {
            "1. open": "395.9000",
            "2. high": "397.0000",
            "3. low": "393.1000",
            "4. close": "396.6000",
            "5. volume": "22063869"
        },
        "2025-02-13": {
            "1. open": "396.2000",
            "2. high": "397.6000",
            "3. low": "393.0000",
            "4. close": "395.4000",
            "5. volume": "7892846"
        },
        "2025-02-12": {
            "1. open": "393.2000",
            "2. high": "395.3000",
            "3. low": "389.6000",
            "4. close": "392.9000",
            "5. volume": "8330221"
        },
        "2025-02-11": {
            "1. open": "391.0000",
            "2. high": "398.1000",
            "3. low": "390.2000",
            "4. close": "394.5000",
            "5. volume": "21900010"
        },
        "2025-02-10": {
            "1. open": "387.0000",
            "2. high": "391.0000",
            "3. low": "387.0000",
            "4. close": "389.8000",
            "5. volume": "11537070"
        },
        "2025-02-07": {
            "1. open": "386.0000",
            "2. high": "389.5000",
            "3. low": "386.0000",
            "4. close": "387.3000",
            "5. volume": "8884498"
        },
        "2025-02-06": {
            "1. open": "389.3000",
            "2. high": "391.8000",
            "3. low": "387.0000",
            "4. close": "387.0000",
            "5. volume": "11638850"
        },
        "2025-02-05": {
            "1. open": "376.1000",
            "2. high": "387.8000",
            "3. low": "375.6000",
            "4. close": "387.6000",
            "5. volume": "25475779"
        },
        "2025-02-04": {
            "1. open": "372.1000",
            "2. high": "377.6000",
            "3. low": "370.9000",
            "4. close": "377.4000",
            "5. volume": "11475890"
        },
        "2025-02-03": {
            "1. open": "369.1000",
            "2. high": "372.8000",
            "3. low": "369.1000",
            "4. close": "372.4000",
            "5. volume": "10232010"
        },
        "2025-01-31": {
            "1. open": "373.3000",
            "2. high": "375.1000",
            "3. low": "371.4000",
            "4. close": "372.2000",
            "5. volume": "15480340"
        },
        "2025-01-30": {
            "1. open": "369.0000",
            "2. high": "374.5000",
            "3. low": "369.0000",
            "4. close": "373.7000",
            "5. volume": "10603500"
        },
        "2025-01-29": {
            "1. open": "370.4000",
            "2. high": "372.2000",
            "3. low": "368.6000",
            "4. close": "368.8000",
            "5. volume": "14401810"
        },
        "2025-01-28": {
            "1. open": "365.1000",
            "2. high": "371.7000",
            "3. low": "364.5000",
            "4. close": "370.6000",
            "5. volume": "7488482"
        },
        "2025-01-27": {
            "1. open": "359.9000",
            "2. high": "366.5000",
            "3. low": "359.6000",
            "4. close": "363.7000",
            "5. volume": "18743811"
        }
    }
}